admin_logs/__init__.py
admin_logs/admin.py
admin_logs/apps.py
admin_logs/decorators.py
admin_logs/log.py
admin_logs/middleware.py
admin_logs/models.py
admin_logs/tasks.py
admin_logs/tests.py
admin_logs/views.py
admin_logs/backends/__init__.py
admin_logs/backends/database.py
admin_logs/migrations/0001_initial.py
admin_logs/migrations/0002_auto_20160418_0349.py
admin_logs/migrations/0003_auto_20160922_1515.py
admin_logs/migrations/0004_auto_20171101_0350.py
admin_logs/migrations/0005_auto_20171101_1335.py
admin_logs/migrations/0006_auto_20180620_0428.py
admin_logs/migrations/__init__.py
admin_logs/static/css/admin_logs/styles.css
admin_logs/static/images/admin_logs/minus.png
admin_logs/static/images/admin_logs/plus.png
admin_logs/static/js/admin_logs/common.js
admin_logs/templates/admin_logs/admin_logs_list.html
admin_logs-0.2.14.dist-info/DESCRIPTION.rst
admin_logs-0.2.14.dist-info/METADATA
admin_logs-0.2.14.dist-info/RECORD
admin_logs-0.2.14.dist-info/WHEEL
admin_logs-0.2.14.dist-info/metadata.json
admin_logs-0.2.14.dist-info/top_level.txt
