Metadata-Version: 2.0
Name: admin-logs
Version: 0.2.14
Summary: Admin logs for django like in Google Application Engine
Home-page: https://github.com/FerumFlex/admin_logs
Author: Anton Pomeschenko
Author-email: ferumflex@gmail.com
License: MIT
Platform: UNKNOWN
Classifier: Framework :: Django
Classifier: Intended Audience :: Developers
Classifier: Intended Audience :: System Administrators
Classifier: Operating System :: OS Independent
Classifier: Topic :: Software Development
Classifier: Programming Language :: Python :: 3
Classifier: Programming Language :: Python :: 3.4
Classifier: Programming Language :: Python :: 3.5
Classifier: Programming Language :: Python :: 3.6
Classifier: Framework :: Django
Classifier: Framework :: Django :: 1.7
Classifier: Framework :: Django :: 1.8
Classifier: Framework :: Django :: 1.9
Classifier: Framework :: Django :: 1.10
Classifier: Framework :: Django :: 1.11
Requires-Dist: Django (>=1.7)
Requires-Dist: celery (>=4.1)
Requires-Dist: django-picklefield
